jicagile
