Metadata-Version: 1.1
Name: jicagile
Version: 0.3.0
Summary: Lighweight command line tool for agile project management
Home-page: https://github.com/JIC-CSB/jicagile
Author: Tjelvar Olsson
Author-email: tjelvar.olsson@jic.ac.uk
License: MIT
Download-URL: https://github.com/JIC-CSB/jicagile/tarball/0.3.0
Keywords: agile,project,management
Platform: UNKNOWN
Classifier: Development Status :: 3 - Alpha
Classifier: Intended Audience :: Developers
Classifier: License :: OSI Approved :: MIT License
Classifier: Natural Language :: English
Classifier: Programming Language :: Python
Classifier: Programming Language :: Python :: 2
Classifier: Programming Language :: Python :: 2.7
